pydrop/__init__.py
pydrop/pydrop.py
pydrop-0.0.6.dist-info/METADATA
pydrop-0.0.6.dist-info/RECORD
pydrop-0.0.6.dist-info/WHEEL
pydrop-0.0.6.dist-info/entry_points.txt
pydrop-0.0.6.dist-info/top_level.txt
